{
  "$schema": "https://ui.shadcn.com/schema/registry.json",
  "homepage": "https://faststack.ai/registry",
  "name": "18_up_rating",
  "type": "registry:ui",
  "author": "Nicolas Angelo <nicolas@faststack.ai>",
  "dependencies": [],
  "devDependencies": [],
  "registryDependencies": [],
  "files": [
    {
      "type": "registry:ui",
      "path": "mdi/filled/18_up_rating.svg",
      "target": "components/ui/mdi/filled/18_up_rating.tsx",
      "content": "import type { SVGProps } from \"react\";\n\nconst EighteenUpRating = (props: SVGProps<SVGSVGElement>) => (\n  <svg\n    xmlns=\"http://www.w3.org/2000/svg\"\n    viewBox=\"0 0 24 24\"\n    fill=\"currentColor\"\n    {...props}\n  >\n    <path d=\"M13 12.5h1.5V14H13zm0-2.5h1.5v1.5H13z\" />\n    <path d=\"M19 3H5c-1.1 0-2 .9-2 2v14c0 1.1.9 2 2 2h14c1.1 0 2-.9 2-2V5c0-1.1-.9-2-2-2zm-9 12H8.5v-4.5H7V9h3v6zm6-1c0 .55-.45 1-1 1h-2.5c-.55 0-1-.45-1-1v-4c0-.55.45-1 1-1H15c.55 0 1 .45 1 1v4z\" />\n  </svg>\n);\n\nexport default EighteenUpRating;\n"
    }
  ]
}