{
  "$schema": "https://ui.shadcn.com/schema/registry.json",
  "homepage": "https://faststack.ai/registry",
  "name": "view_agenda",
  "type": "registry:ui",
  "author": "Nicolas Angelo <nicolas@faststack.ai>",
  "dependencies": [],
  "devDependencies": [],
  "registryDependencies": [],
  "files": [
    {
      "type": "registry:ui",
      "path": "mdi/round/view_agenda.svg",
      "target": "components/ui/mdi/round/view_agenda.tsx",
      "content": "import type { SVGProps } from \"react\";\n\nconst ViewAgenda = (props: SVGProps<SVGSVGElement>) => (\n  <svg\n    xmlns=\"http://www.w3.org/2000/svg\"\n    viewBox=\"0 0 24 24\"\n    fill=\"currentColor\"\n    {...props}\n  >\n    <path d=\"M19 13H5c-1.1 0-2 .9-2 2v4c0 1.1.9 2 2 2h14c1.1 0 2-.9 2-2v-4c0-1.1-.9-2-2-2zm0-10H5c-1.1 0-2 .9-2 2v4c0 1.1.9 2 2 2h14c1.1 0 2-.9 2-2V5c0-1.1-.9-2-2-2z\" />\n  </svg>\n);\n\nexport default ViewAgenda;\n"
    }
  ]
}