{
  "$schema": "https://ui.shadcn.com/schema/registry.json",
  "homepage": "https://faststack.ai/registry",
  "name": "add_circle",
  "type": "registry:ui",
  "author": "Nicolas Angelo <nicolas@faststack.ai>",
  "dependencies": [],
  "devDependencies": [],
  "registryDependencies": [],
  "files": [
    {
      "type": "registry:ui",
      "path": "mdi/sharp/add_circle.svg",
      "target": "components/ui/mdi/sharp/add_circle.tsx",
      "content": "import type { SVGProps } from \"react\";\n\nconst AddCircle = (props: SVGProps<SVGSVGElement>) => (\n  <svg\n    xmlns=\"http://www.w3.org/2000/svg\"\n    viewBox=\"0 0 24 24\"\n    fill=\"currentColor\"\n    {...props}\n  >\n    <path d=\"M12 2C6.48 2 2 6.48 2 12s4.48 10 10 10 10-4.48 10-10S17.52 2 12 2zm5 11h-4v4h-2v-4H7v-2h4V7h2v4h4v2z\" />\n  </svg>\n);\n\nexport default AddCircle;\n"
    }
  ]
}