{
  "$schema": "https://ui.shadcn.com/schema/registry.json",
  "homepage": "https://faststack.ai/registry",
  "name": "headphones_battery",
  "type": "registry:ui",
  "author": "Nicolas Angelo <nicolas@faststack.ai>",
  "dependencies": [],
  "devDependencies": [],
  "registryDependencies": [],
  "files": [
    {
      "type": "registry:ui",
      "path": "mdi/sharp/headphones_battery.svg",
      "target": "components/ui/mdi/sharp/headphones_battery.tsx",
      "content": "import type { SVGProps } from \"react\";\n\nconst HeadphonesBattery = (props: SVGProps<SVGSVGElement>) => (\n  <svg\n    xmlns=\"http://www.w3.org/2000/svg\"\n    viewBox=\"0 0 24 24\"\n    fill=\"currentColor\"\n    {...props}\n  >\n    <path d=\"M20 7V6h-2v1h-2v11h6V7zM8 6c-3.31 0-6 2.69-6 6v6h4v-5H3.5v-1c0-2.48 2.02-4.5 4.5-4.5s4.5 2.02 4.5 4.5v1H10v5h4v-6c0-3.31-2.69-6-6-6z\" />\n  </svg>\n);\n\nexport default HeadphonesBattery;\n"
    }
  ]
}