{
  "$schema": "https://ui.shadcn.com/schema/registry.json",
  "homepage": "https://faststack.ai/registry",
  "name": "local_cafe",
  "type": "registry:ui",
  "author": "Nicolas Angelo <nicolas@faststack.ai>",
  "dependencies": [],
  "devDependencies": [],
  "registryDependencies": [],
  "files": [
    {
      "type": "registry:ui",
      "path": "mdi/outlined/local_cafe.svg",
      "target": "components/ui/mdi/outlined/local_cafe.tsx",
      "content": "import type { SVGProps } from \"react\";\n\nconst LocalCafe = (props: SVGProps<SVGSVGElement>) => (\n  <svg\n    xmlns=\"http://www.w3.org/2000/svg\"\n    viewBox=\"0 0 24 24\"\n    fill=\"currentColor\"\n    {...props}\n  >\n    <path d=\"M16 5v8c0 1.1-.9 2-2 2H8c-1.1 0-2-.9-2-2V5h10m4-2H4v10c0 2.21 1.79 4 4 4h6c2.21 0 4-1.79 4-4v-3h2c1.11 0 2-.89 2-2V5c0-1.11-.89-2-2-2zm-2 5V5h2v3h-2zm2 11H2v2h18v-2z\" />\n  </svg>\n);\n\nexport default LocalCafe;\n"
    }
  ]
}