{
  "$schema": "https://ui.shadcn.com/schema/registry.json",
  "homepage": "https://faststack.ai/registry",
  "name": "phonelink_erase",
  "type": "registry:ui",
  "author": "Nicolas Angelo <nicolas@faststack.ai>",
  "dependencies": [],
  "devDependencies": [],
  "registryDependencies": [],
  "files": [
    {
      "type": "registry:ui",
      "path": "mdi/outlined/phonelink_erase.svg",
      "target": "components/ui/mdi/outlined/phonelink_erase.tsx",
      "content": "import type { SVGProps } from \"react\";\n\nconst PhonelinkErase = (props: SVGProps<SVGSVGElement>) => (\n  <svg\n    xmlns=\"http://www.w3.org/2000/svg\"\n    viewBox=\"0 0 24 24\"\n    fill=\"currentColor\"\n    {...props}\n  >\n    <path d=\"m13 8.2-1-1-4 4-4-4-1 1 4 4-4 4 1 1 4-4 4 4 1-1-4-4 4-4zM19 1H9c-1.1 0-2 .9-2 2v3h2V4h10v16H9v-2H7v3c0 1.1.9 2 2 2h10c1.1 0 2-.9 2-2V3c0-1.1-.9-2-2-2z\" />\n  </svg>\n);\n\nexport default PhonelinkErase;\n"
    }
  ]
}